imgkerneliu/__init__.py
imgkerneliu/imgconv.py
imgkerneliu/kernels.py
imgkerneliu-0.0.3.dist-info/LICENSE
imgkerneliu-0.0.3.dist-info/METADATA
imgkerneliu-0.0.3.dist-info/WHEEL
imgkerneliu-0.0.3.dist-info/top_level.txt
imgkerneliu-0.0.3.dist-info/RECORD
