Metadata-Version: 2.1
Name: imgkerneliu
Version: 0.0.3
Summary: Image kernel.
Home-page: https://github.com/liuyunclouder/imgkerneliu
Author: ken
Author-email: liuyunclouder@gmail.com
License: UNKNOWN
Platform: UNKNOWN
Classifier: Programming Language :: Python :: 3
Classifier: License :: OSI Approved :: MIT License
Classifier: Operating System :: OS Independent
Requires-Python: >=3.6
License-File: LICENSE
